[
  {
    "timestamp": "2025-12-28T10:30:52.813963",
    "args": {
      "input": "data/timeseries.h5",
      "max_length": 512,
      "direction": "bi",
      "random_seed": 19,
      "num_samples": 2048,
      "epochs": 3,
      "batch_size": 16,
      "lr": 0.001,
      "hidden_size": 64,
      "output_dir": "output/simple_rnn",
      "output_name": "baseline_v16_masking_sim.pt",
      "device": "auto",
      "use_flow": true,
      "min_size": 5,
      "max_size": 100,
      "mask_portion": 0.4,
      "mock_sinusoid": true,
      "mock_noise": 0.2,
      "mode": "parallel",
      "K": 64
    }
  },
  {
    "timestamp": "2025-12-28T10:36:41.577792",
    "args": {
      "input": "data/timeseries.h5",
      "max_length": 512,
      "direction": "bi",
      "random_seed": 19,
      "num_samples": 2048,
      "epochs": 3,
      "batch_size": 16,
      "lr": 0.001,
      "hidden_size": 64,
      "output_dir": "output/simple_rnn",
      "output_name": "baseline_v16_masking_sim.pt",
      "device": "auto",
      "use_flow": true,
      "min_size": 5,
      "max_size": 100,
      "mask_portion": 0.4,
      "mock_sinusoid": true,
      "mock_noise": 0.2,
      "mode": "parallel",
      "K": 64
    }
  },
  {
    "timestamp": "2025-12-30T19:26:08.638241",
    "args": {
      "input": "data/timeseries.h5",
      "max_length": 2048,
      "direction": "bi",
      "random_seed": 19,
      "num_samples": 8192,
      "epochs": 100,
      "batch_size": 16,
      "lr": 0.001,
      "hidden_size": 64,
      "output_dir": "output/simple_rnn",
      "output_name": "baseline_v17_real_final.pt",
      "device": "auto",
      "use_flow": true,
      "min_size": 5,
      "max_size": 100,
      "mask_portion": 0.4,
      "mock_sinusoid": false,
      "mock_noise": 0.1,
      "mode": "parallel",
      "K": 64
    }
  },
  {
    "timestamp": "2025-12-30T19:26:20.670982",
    "args": {
      "input": "data/timeseries.h5",
      "max_length": 2048,
      "direction": "bi",
      "random_seed": 19,
      "num_samples": 7911,
      "epochs": 100,
      "batch_size": 16,
      "lr": 0.001,
      "hidden_size": 64,
      "output_dir": "output/simple_rnn",
      "output_name": "baseline_v17_real_final.pt",
      "device": "auto",
      "use_flow": true,
      "min_size": 5,
      "max_size": 100,
      "mask_portion": 0.4,
      "mock_sinusoid": false,
      "mock_noise": 0.1,
      "mode": "parallel",
      "K": 64
    }
  },
  {
    "timestamp": "2025-12-30T20:11:19.629704",
    "args": {
      "input": "data/timeseries.h5",
      "max_length": 2048,
      "direction": "bi",
      "random_seed": 19,
      "num_samples": 2048,
      "epochs": 100,
      "batch_size": 16,
      "lr": 0.001,
      "hidden_size": 64,
      "output_dir": "output/simple_rnn",
      "output_name": "baseline_v17_real_final.pt",
      "device": "auto",
      "use_flow": true,
      "min_size": 5,
      "max_size": 100,
      "mask_portion": 0.4,
      "mock_sinusoid": false,
      "mock_noise": 0.1,
      "mode": "parallel",
      "K": 64
    }
  },
  {
    "timestamp": "2025-12-30T20:32:53.251104",
    "args": {
      "input": "data/timeseries.h5",
      "max_length": 1024,
      "direction": "bi",
      "random_seed": 19,
      "num_samples": 2048,
      "epochs": 100,
      "batch_size": 16,
      "lr": 0.001,
      "hidden_size": 64,
      "output_dir": "output/simple_rnn",
      "output_name": "baseline_v17_real_final.pt",
      "device": "auto",
      "use_flow": true,
      "min_size": 5,
      "max_size": 100,
      "mask_portion": 0.4,
      "mock_sinusoid": false,
      "mock_noise": 0.1,
      "mode": "parallel",
      "K": 64
    }
  },
  {
    "timestamp": "2026-01-22T14:11:24.631707",
    "args": {
      "input": "data/timeseries_x.h5",
      "max_length": 1024,
      "direction": "bi",
      "random_seed": 19,
      "num_samples": 2048,
      "epochs": 50,
      "batch_size": 16,
      "lr": 0.001,
      "hidden_size": 64,
      "output_dir": "output/simple_rnn",
      "output_name": "baseline_v18_stellar_params.pt",
      "device": "auto",
      "use_flow": true,
      "min_size": 5,
      "max_size": 100,
      "mask_portion": 0.4,
      "mock_sinusoid": false,
      "mock_noise": 0.1,
      "mode": "parallel",
      "K": 256,
      "k_spacing": "fibonacci",
      "use_metadata": true
    }
  },
  {
    "timestamp": "2026-01-22T14:35:40.582482",
    "args": {
      "input": "data/timeseries_x.h5",
      "max_length": 1024,
      "direction": "bi",
      "random_seed": 19,
      "num_samples": 2048,
      "epochs": 50,
      "batch_size": 16,
      "lr": 0.001,
      "hidden_size": 64,
      "output_dir": "output/simple_rnn",
      "output_name": "baseline_v18_stellar_params.pt",
      "device": "auto",
      "use_flow": true,
      "min_size": 5,
      "max_size": 100,
      "mask_portion": 0.4,
      "mock_sinusoid": false,
      "mock_noise": 0.1,
      "mode": "parallel",
      "K": 256,
      "k_spacing": "fibonacci",
      "use_metadata": true
    }
  },
  {
    "timestamp": "2026-01-22T14:47:09.958076",
    "args": {
      "input": "data/timeseries_x.h5",
      "max_length": 1024,
      "direction": "bi",
      "random_seed": 19,
      "num_samples": 2048,
      "epochs": 100,
      "batch_size": 16,
      "lr": 0.001,
      "hidden_size": 64,
      "output_dir": "output/simple_rnn",
      "output_name": "baseline_v18_fib_k.pt",
      "device": "auto",
      "use_flow": true,
      "min_size": 5,
      "max_size": 100,
      "mask_portion": 0.4,
      "mock_sinusoid": false,
      "mock_noise": 0.1,
      "mode": "parallel",
      "K": 256,
      "k_spacing": "fibonacci",
      "use_metadata": false
    }
  },
  {
    "timestamp": "2026-01-22T14:49:12.801289",
    "args": {
      "input": "data/timeseries_x.h5",
      "max_length": 1024,
      "direction": "bi",
      "random_seed": 19,
      "num_samples": 2048,
      "epochs": 100,
      "batch_size": 16,
      "lr": 0.001,
      "hidden_size": 64,
      "output_dir": "output/simple_rnn",
      "output_name": "baseline_v18_fib_k.pt",
      "device": "auto",
      "use_flow": true,
      "min_size": 5,
      "max_size": 100,
      "mask_portion": 0.4,
      "mock_sinusoid": false,
      "mock_noise": 0.1,
      "mode": "parallel",
      "K": 256,
      "k_spacing": "fibonacci",
      "use_metadata": false
    }
  },
  {
    "timestamp": "2026-01-22T14:54:19.791836",
    "args": {
      "input": "data/timeseries_x.h5",
      "max_length": 1024,
      "direction": "bi",
      "random_seed": 19,
      "num_samples": 2048,
      "epochs": 100,
      "batch_size": 16,
      "lr": 0.001,
      "hidden_size": 64,
      "output_dir": "output/simple_rnn",
      "output_name": "baseline_v18_fib_k.pt",
      "device": "auto",
      "use_flow": true,
      "min_size": 5,
      "max_size": 100,
      "mask_portion": 0.4,
      "mock_sinusoid": false,
      "mock_noise": 0.1,
      "mode": "parallel",
      "K": 256,
      "k_spacing": "fibonacci",
      "use_metadata": false
    }
  },
  {
    "timestamp": "2026-01-22T15:18:00.248565",
    "args": {
      "input": "data/timeseries_x.h5",
      "max_length": 512,
      "direction": "bi",
      "random_seed": 19,
      "num_samples": 1024,
      "epochs": 40,
      "batch_size": 16,
      "lr": 0.001,
      "hidden_size": 64,
      "output_dir": "output/simple_rnn",
      "output_name": "baseline_v18_fib_k.pt",
      "device": "auto",
      "use_flow": true,
      "min_size": 5,
      "max_size": 100,
      "mask_portion": 0.4,
      "mock_sinusoid": false,
      "mock_noise": 0.1,
      "mode": "parallel",
      "K": 128,
      "k_spacing": "fibonacci",
      "use_metadata": false
    }
  }
]